{"nodes": [{"id": "lib_idb", "label": "IDB Queue Library", "file_type": "code", "source_file": "src/lib/idb.ts", "source_location": null, "source_url": null, "captured_at": null, "author": null, "contributor": null}, {"id": "lib_idb_getdb", "label": "getDB Function", "file_type": "code", "source_file": "src/lib/idb.ts", "source_location": "15", "source_url": null, "captured_at": null, "author": null, "contributor": null}, {"id": "lib_idb_wines_local", "label": "wines_local IDB Store", "file_type": "code", "source_file": "src/lib/idb.ts", "source_location": "18", "source_url": null, "captured_at": null, "author": null, "contributor": null}, {"id": "lib_idb_tastings_local", "label": "tastings_local IDB Store", "file_type": "code", "source_file": "src/lib/idb.ts", "source_location": "19", "source_url": null, "captured_at": null, "author": null, "contributor": null}, {"id": "lib_idb_sync_queue", "label": "sync_queue IDB Store", "file_type": "code", "source_file": "src/lib/idb.ts", "source_location": "20", "source_url": null, "captured_at": null, "author": null, "contributor": null}, {"id": "lib_idb_addtoqueue", "label": "addToQueue Function", "file_type": "code", "source_file": "src/lib/idb.ts", "source_location": "68", "source_url": null, "captured_at": null, "author": null, "contributor": null}], "edges": [{"source": "lib_idb_getdb", "target": "lib_idb_wines_local", "relation": "implements", "confidence": "EXTRACTED", "confidence_score": 1.0, "source_file": "src/lib/idb.ts", "source_location": "19", "weight": 1.0}, {"source": "lib_idb_getdb", "target": "lib_idb_tastings_local", "relation": "implements", "confidence": "EXTRACTED", "confidence_score": 1.0, "source_file": "src/lib/idb.ts", "source_location": "20", "weight": 1.0}, {"source": "lib_idb_getdb", "target": "lib_idb_sync_queue", "relation": "implements", "confidence": "EXTRACTED", "confidence_score": 1.0, "source_file": "src/lib/idb.ts", "source_location": "21", "weight": 1.0}], "hyperedges": []}